[
	{
		"archived": false,
		"autoDevopsDeployStrategy": "CONTINUOUS",
		"autoDevopsEnabled": false,
		"autocloseReferencedIssues": true,
		"canCreateMergeRequestIn": true,
		"ciConfigPath": "",
		"ciDefaultGitDepth": 20,
		"ciForwardDeploymentEnabled": true,
		"containerRegistryEnabled": true,
		"createdAt": 1657122070303,
		"creatorId": 12006469,
		"defaultBranch": "main",
		"description": "",
		"emptyRepo": false,
		"forksCount": 0,
		"httpUrlToRepo": "https://gitlab.com/zc_202207062305/test02.git",
		"id": 37620666,
		"importStatus": "NONE",
		"issuesEnabled": true,
		"jobsEnabled": true,
		"lastActivityAt": 1657122070303,
		"lfsEnabled": true,
		"mergeMethod": "MERGE",
		"mergeRequestsEnabled": true,
		"name": "test02",
		"nameWithNamespace": "zc_202207062305 / test02",//ÏîÄ¿µØÖ·
		"namespace": {
			"fullPath": "zc_202207062305",
			"id": 55285585,
			"kind": "group",
			"name": "zc_202207062305",
			"path": "zc_202207062305",
			"webUrl": "https://gitlab.com/groups/zc_202207062305"
		},
		"onlyAllowMergeIfAllDiscussionsAreResolved": false,
		"onlyAllowMergeIfPipelineSucceeds": false,
		"openIssuesCount": 0,
		"packagesEnabled": true,
		"path": "test02",
		"pathWithNamespace": "zc_202207062305/test02",
		"permissions": {
			"groupAccess": {
				"accessLevel": "OWNER",
				"notificationLevel": 3
			}
		},
		"printingMergeRequestLinkEnabled": true,
		"publicJobs": true,
		"readmeUrl": "https://gitlab.com/zc_202207062305/test02/-/blob/main/README.md",
		"removeSourceBranchAfterMerge": true,
		"requestAccessEnabled": true,
		"resolveOutdatedDiffDiscussions": false,
		"sharedRunnersEnabled": true,
		"sharedWithGroups": [],
		"snippetsEnabled": true,
		"squashOption": "DEFAULT_OFF",
		"sshUrlToRepo": "git@gitlab.com:zc_202207062305/test02.git",
		"starCount": 0,
		"tagList": [],
		"visibility": "PRIVATE",
		"webUrl": "https://gitlab.com/zc_202207062305/test02",
		"wikiEnabled": true
	},
	{
		"archived": false,
		"autoDevopsDeployStrategy": "CONTINUOUS",
		"autoDevopsEnabled": false,
		"autocloseReferencedIssues": true,
		"canCreateMergeRequestIn": true,
		"ciConfigPath": "",
		"ciDefaultGitDepth": 20,
		"ciForwardDeploymentEnabled": true,
		"containerRegistryEnabled": true,
		"createdAt": 1657121975490,
		"creatorId": 12006469,
		"defaultBranch": "main",
		"description": "",
		"emptyRepo": false,
		"forksCount": 0,
		"httpUrlToRepo": "https://gitlab.com/zc_202207062305/test01.git",
		"id": 37620622,
		"importStatus": "NONE",
		"issuesEnabled": true,
		"jobsEnabled": true,
		"lastActivityAt": 1657121975490,
		"lfsEnabled": true,
		"mergeMethod": "MERGE",
		"mergeRequestsEnabled": true,
		"name": "test01",
		"nameWithNamespace": "zc_202207062305 / test01",
		"namespace": {
			"fullPath": "zc_202207062305",
			"id": 55285585,
			"kind": "group",
			"name": "zc_202207062305",
			"path": "zc_202207062305",
			"webUrl": "https://gitlab.com/groups/zc_202207062305"
		},
		"onlyAllowMergeIfAllDiscussionsAreResolved": false,
		"onlyAllowMergeIfPipelineSucceeds": false,
		"openIssuesCount": 0,
		"packagesEnabled": true,
		"path": "test01",
		"pathWithNamespace": "zc_202207062305/test01",
		"permissions": {
			"groupAccess": {
				"accessLevel": "OWNER",
				"notificationLevel": 3
			}
		},
		"printingMergeRequestLinkEnabled": true,
		"publicJobs": true,
		"readmeUrl": "https://gitlab.com/zc_202207062305/test01/-/blob/main/README.md",
		"removeSourceBranchAfterMerge": true,
		"requestAccessEnabled": true,
		"resolveOutdatedDiffDiscussions": false,
		"sharedRunnersEnabled": true,
		"sharedWithGroups": [],
		"snippetsEnabled": true,
		"squashOption": "DEFAULT_OFF",
		"sshUrlToRepo": "git@gitlab.com:zc_202207062305/test01.git",
		"starCount": 0,
		"tagList": [],
		"visibility": "PRIVATE",
		"webUrl": "https://gitlab.com/zc_202207062305/test01",
		"wikiEnabled": true
	},
	{
		"archived": false,
		"autoDevopsDeployStrategy": "CONTINUOUS",
		"autoDevopsEnabled": false,
		"autocloseReferencedIssues": true,
		"canCreateMergeRequestIn": true,
		"ciConfigPath": "",
		"ciDefaultGitDepth": 20,
		"ciForwardDeploymentEnabled": true,
		"containerRegistryEnabled": true,
		"createdAt": 1657121579479,
		"creatorId": 12006469,
		"defaultBranch": "main",
		"description": "",
		"emptyRepo": false,
		"forksCount": 0,
		"httpUrlToRepo": "https://gitlab.com/zhengchaogit2018/testgit.git",
		"id": 37620444,
		"importStatus": "NONE",
		"issuesEnabled": true,
		"jobsEnabled": true,
		"lastActivityAt": 1657121579479,
		"lfsEnabled": true,
		"mergeMethod": "MERGE",
		"mergeRequestsEnabled": true,
		"name": "testgit",
		"nameWithNamespace": "zhengchaogit2018 / testgit",
		"namespace": {
			"avatarUrl": "https://secure.gravatar.com/avatar/20b16c0c14a8a83a1c9908d7e79474ef?s=80&d=identicon",
			"fullPath": "zhengchaogit2018",
			"id": 55284140,
			"kind": "user",
			"name": "zhengchaogit2018",
			"path": "zhengchaogit2018",
			"webUrl": "https://gitlab.com/zhengchaogit2018"
		},
		"onlyAllowMergeIfAllDiscussionsAreResolved": false,
		"onlyAllowMergeIfPipelineSucceeds": false,
		"openIssuesCount": 0,
		"owner": {
			"avatarUrl": "https://secure.gravatar.com/avatar/20b16c0c14a8a83a1c9908d7e79474ef?s=80&d=identicon",
			"id": 12006469,
			"name": "zhengchaogit2018",
			"state": "active",
			"username": "zhengchaogit2018",
			"webUrl": "https://gitlab.com/zhengchaogit2018"
		},
		"packagesEnabled": true,
		"path": "testgit",
		"pathWithNamespace": "zhengchaogit2018/testgit",
		"permissions": {
			"projectAccess": {
				"accessLevel": "OWNER",
				"notificationLevel": 3
			}
		},
		"printingMergeRequestLinkEnabled": true,
		"publicJobs": true,
		"readmeUrl": "https://gitlab.com/zhengchaogit2018/testgit/-/blob/main/README.md",
		"removeSourceBranchAfterMerge": true,
		"requestAccessEnabled": true,
		"resolveOutdatedDiffDiscussions": false,
		"sharedRunnersEnabled": true,
		"sharedWithGroups": [
			{
				"groupAccessLevel": "GUEST",
				"groupFullPath": "zc_202207062305",
				"groupId": 55285585,
				"groupName": "zc_202207062305"
			}
		],
		"snippetsEnabled": true,
		"squashOption": "DEFAULT_OFF",
		"sshUrlToRepo": "git@gitlab.com:zhengchaogit2018/testgit.git",
		"starCount": 0,
		"tagList": [],
		"visibility": "PRIVATE",
		"webUrl": "https://gitlab.com/zhengchaogit2018/testgit",
		"wikiEnabled": true
	}
]